resultsdb_conventions/__init__.py
resultsdb_conventions/base.py
resultsdb_conventions/fedora.py
resultsdb_conventions/fedoracoreos.py
resultsdb_conventions/helpers.py
resultsdb_conventions/prodmd.py
resultsdb_conventions-3.0.2.dist-info/COPYING
resultsdb_conventions-3.0.2.dist-info/METADATA
resultsdb_conventions-3.0.2.dist-info/WHEEL
resultsdb_conventions-3.0.2.dist-info/top_level.txt
resultsdb_conventions-3.0.2.dist-info/RECORD
