Metadata-Version: 2.1
Name: resultsdb-conventions
Version: 3.0.2
Summary: Module for conveniently reporting to ResultsDB following conventions
Home-page: https://pagure.io/fedora-qa/resultsdb_conventions
Author: Adam Williamson
Author-email: awilliam@redhat.com
License: GPLv3+
Keywords: fedora rhel epel resultsdb test taskotron
Classifier: Development Status :: 5 - Production/Stable
Classifier: Topic :: Utilities
Classifier: License :: OSI Approved :: GNU General Public License v3 or later (GPLv3+)
License-File: COPYING
Requires-Dist: cached-property
Requires-Dist: resultsdb-api
Requires-Dist: productmd
Provides-Extra: fedora
Requires-Dist: fedfind ; extra == 'fedora'
